leetcode_local_runner/__init__.py
leetcode_local_runner/constants.py
leetcode_local_runner/display.py
leetcode_local_runner/runner.py
leetcode_local_runner/test_case.py
leetcode_local_runner-0.0.1.dist-info/LICENSE
leetcode_local_runner-0.0.1.dist-info/METADATA
leetcode_local_runner-0.0.1.dist-info/WHEEL
leetcode_local_runner-0.0.1.dist-info/RECORD
