Metadata-Version: 2.3
Name: leetcode-local-runner
Version: 0.0.1
Summary: A python package with tools to let you try coding problems and check your code against your own test cases.
License: MIT License
Keywords: runner,helper,leetcode,project-euler
Author: Anurag Shenoy
Author-email: anuragshenoy21@gmail.com
Requires-Python: >=3.10
Classifier: Development Status :: 2 - Pre-Alpha
Classifier: Environment :: Console
Classifier: Intended Audience :: Education
Classifier: Intended Audience :: End Users/Desktop
Classifier: License :: OSI Approved :: MIT License
Classifier: Natural Language :: English
Classifier: Operating System :: OS Independent
Classifier: Programming Language :: Python :: 3.10
Classifier: Topic :: Education
Requires-Dist: numpy (>=1.21.4)
Requires-Dist: termcolor (>=2.4.0)
Project-URL: Documentation, https://github.com/shenoy-anurag/leetcode-runner
Project-URL: Funding, https://buymeacoffee.com/anuragshenoy
Project-URL: Homepage, https://github.com/shenoy-anurag/leetcode-runner
Project-URL: Issues, https://github.com/shenoy-anurag/leetcode-runner/issues
Project-URL: Repository, https://github.com/shenoy-anurag/leetcode-runner
